aiogram_media_group/__init__.py
aiogram_media_group/handler.py
aiogram_media_group/storages/__init__.py
aiogram_media_group/storages/base.py
aiogram_media_group/storages/memory.py
aiogram_media_group/storages/mongo.py
aiogram_media_group/storages/redis.py
aiogram_media_group-0.5.0.dist-info/LICENSE
aiogram_media_group-0.5.0.dist-info/WHEEL
aiogram_media_group-0.5.0.dist-info/METADATA
aiogram_media_group-0.5.0.dist-info/RECORD
