Metadata-Version: 2.1
Name: aiogram-media-group
Version: 0.5.0
Summary: Aiogram handler for media groups (also known as albums)
Home-page: https://github.com/deptyped/aiogram-media-group
License: MIT
Author: deptyped
Author-email: deptyped@gmail.com
Requires-Python: >=3.7,<4.0
Classifier: License :: OSI Approved :: MIT License
Classifier: Programming Language :: Python :: 3
Classifier: Programming Language :: Python :: 3.10
Classifier: Programming Language :: Python :: 3.7
Classifier: Programming Language :: Python :: 3.8
Classifier: Programming Language :: Python :: 3.9
Requires-Dist: aiogram (>2)
Project-URL: Repository, https://github.com/deptyped/aiogram-media-group
